decasu/__init__.py
decasu/configuration.py
decasu/decasu_globals.py
decasu/decasu_hpix_mapper.py
decasu/decasu_tile_mapper.py
decasu/healpix_consolidator.py
decasu/multi_healpix_mapper.py
decasu/multi_tile_mapper.py
decasu/region_mapper.py
decasu/simple_healpix_mapper.py
decasu/utils.py
decasu/wcs_table.py
decasu-0.7.2.dist-info/LICENSE
decasu-0.7.2.dist-info/METADATA
decasu-0.7.2.dist-info/WHEEL
decasu-0.7.2.dist-info/entry_points.txt
decasu-0.7.2.dist-info/top_level.txt
decasu-0.7.2.dist-info/RECORD
