Metadata-Version: 2.1
Name: decasu
Version: 0.7.2
Summary: DECam Survey Property Maps using healsparse
Home-page: https://github.com/erykoff/decasu
Author: Eli Rykoff and others
Author-email: erykoff@stanford.edu
License: UNKNOWN
Platform: UNKNOWN
License-File: LICENSE
